vivado1/MyCpu单/SingleCycleCPU_new - 副本/SingleCycleCPU_new.srcs/sources_1/new/ALU.v
`timescale 1ns / 1ps
module ALU(
    // 定义ALU模块的输入和输出端口
    input [31:0] ReadData1,      // 第一个操作数，来自寄存器文件
    input [31:0] ReadData2,      // 第二个操作数，来自寄存器文件
    input [31:0] Ext,            // 扩展后的立即数（用于某些指令）
    input [4:0] Sa,              // 移位量（通常由shamt字段提供）
    input [2:0] ALUop,           // 指定要执行的操作类型
    input ALUSrcA,               // 控制信号：选择InA的来源（ReadData1或Sa）
    input ALUSrcB,               // 控制信号：选择InB的来源（ReadData2或Ext）

    output wire zero,            // 输出信号：当Result为0时置1
    output reg [31:0] Result,     // 运算结果输出
    output wire sign              //符号
);

    // 内部连接线，用于表示实际参与运算的操作数
    wire [31:0] InA;             // 实际参与运算的第一个操作数
    wire [31:0] InB;             // 实际参与运算的第二个操作数

    // 根据控制信号ALUSrcA选择InA的来源：
    // 如果ALUSrcA为1，则InA = {27'b0, Sa}（即高27位为0，低5位为Sa）
    // 否则，InA = ReadData1
    assign InA = ALUSrcA ? {{27{1'b0}}, Sa} : ReadData1;

    // 根据控制信号ALUSrcB选择InB的来源：
    // 如果ALUSrcB为1，则InB = Ext（扩展后的立即数）
    // 否则，InB = ReadData2
    assign InB = ALUSrcB ? Ext : ReadData2;

    // 计算零标志位zero：如果Result为全0，则zero置1；否则为0
    assign zero = (Result == 32'b0) ? 1 : 0;
    assign sign = Result[31];
    // 组合逻辑块，当任何输入发生变化时自动重新计算Result
    always @(*) begin
        case(ALUop) // 根据ALUop的值选择执行不同的运算功能
            3'b000 : 
                Result = InA + InB;                    // 加法操作
            3'b001:
                Result = InA - InB;                    // 减法操作
            3'b010:
                Result = InB << InA[4:0];              // 左移逻辑操作（使用Sa的低5位作为移位数量）
            3'b011:
                Result = InA | InB;                    // 或运算
            3'b100:
                Result = InA & InB;                    // 与运算
            3'b101:
                Result = (InA < InB) ? 32'b1 : 32'b0; // 无符号小于比较（返回32位的1或0）
            3'b110: 
                Result = (((InA < InB) && (InA[31] == InB[31])) || 
                          ((InA[31] == 1'b1) && (InB[31] == 1'b0))) ? 32'b1 : 32'b0; // 带符号小于比较
            3'b111:
                Result = InA ^ InB;                    // 异或运算
            default:
                Result = 32'h00000000;                 // 默认情况，将Result清零
        endcase
    end

endmodule

vivado1/MyCpu单/ALU/ALU.srcs/sim_1/new/ALU_sim.v
`timescale 1ns / 1ps

module ALU_sim();

    // 定义输入信号为寄存器类型
    reg [31:0] ReadData1; // 第一个操作数
    reg [31:0] ReadData2; // 第二个操作数
    reg [31:0] Ext;       // 扩展后的立即数
    reg [4:0] Sa;         // 移位量（5位）
    reg [2:0] ALUop;      // 指定要执行的操作类型
    reg ALUSrcA, ALUSrcB; // 控制信号：选择操作数来源

    // 定义输出信号为线网类型
    wire zero;            // 零标志位
    wire [31:0] Result;   // 运算结果

    // 实例化ALU模块，并连接端口
    ALU uut(
        .ReadData1(ReadData1),
        .ReadData2(ReadData2),
        .Ext(Ext),
        .Sa(Sa),
        .ALUop(ALUop),
        .ALUSrcA(ALUSrcA),
        .ALUSrcB(ALUSrcB),
        .zero(zero),
        .Result(Result)
    );

    initial begin
        // 设置波形记录文件
        $dumpfile("ALU32.vcd"); // 波形文件名
        $dumpvars(0, ALU_sim);  // 记录所有变量

        // 测试序列开始

        // add1: 测试加法操作，ALUSrcA=0, ALUSrcB=0
        #0;
        ReadData1 = 0;
        ReadData2 = 0;
        Ext = 1;
        Sa = 5'b00001; 
        ALUop = 3'b000;
        ALUSrcA = 0;
        ALUSrcB = 0;

        // add2: 测试加法操作，ALUSrcA=1, ALUSrcB=0
        #50;
        ReadData1 = 0;
        ReadData2 = 0;
        Ext = 1;
        Sa = 5'b00001;
        ALUop = 3'b000;
        ALUSrcA = 1;
        ALUSrcB = 0;

        // add3: 测试加法操作，ALUSrcA=0, ALUSrcB=1
        #50;
        ReadData1 = 0;
        ReadData2 = 0;
        Ext = 1;
        Sa = 5'b00001;
        ALUop = 3'b000;
        ALUSrcA = 0;
        ALUSrcB = 1;

        // add4: 测试加法操作，ALUSrcA=1, ALUSrcB=1
        #50;
        ReadData1 = 0;
        ReadData2 = 0;
        Ext = 1;
        Sa = 5'b00001;
        ALUop = 3'b000;
        ALUSrcA = 1;
        ALUSrcB = 1;

        // sub1: 测试减法操作，ALUSrcA=0, ALUSrcB=0
        #50;
        ReadData1 = 32'd1;
        ReadData2 = 32'd2;
        Ext = 32'd3;
        Sa = 5'b00100;
        ALUop = 3'b001;
        ALUSrcA = 0;
        ALUSrcB = 0;

        // sub2: 测试减法操作，ALUSrcA=1, ALUSrcB=0
        #50;
        ReadData1 = 32'd1;
        ReadData2 = 32'd2;
        Ext = 32'd3;
        Sa = 5'b00100;
        ALUop = 3'b001;
        ALUSrcA = 1;
        ALUSrcB = 0;

        // sub3: 测试减法操作，ALUSrcA=0, ALUSrcB=1
        #50;
        ReadData1 = 32'd1;
        ReadData2 = 32'd2;
        Ext = 32'd3;
        Sa = 5'b00100;
        ALUop = 3'b001;
        ALUSrcA = 0;
        ALUSrcB = 1;

        // sub4: 测试减法操作，ALUSrcA=1, ALUSrcB=1
        #50;
        ReadData1 = 32'd1;
        ReadData2 = 32'd2;
        Ext = 32'd3;
        Sa = 5'b00100;
        ALUop = 3'b001;
        ALUSrcA = 1;
        ALUSrcB = 1;

        // left_shift1: 测试左移逻辑操作，ALUSrcA=0, ALUSrcB=0
        #50;
        ReadData1 = 32'd1;
        ReadData2 = 32'd2;
        Ext = 32'd2;
        Sa = 5'b00100;
        ALUop = 3'b010;
        ALUSrcA = 0;
        ALUSrcB = 0;

        // left_shift2: 测试左移逻辑操作，ALUSrcA=1, ALUSrcB=0
        #50;
        ReadData1 = 32'd1;
        ReadData2 = 32'd2;
        Ext = 32'd2;
        Sa = 5'b00100;
        ALUop = 3'b010;
        ALUSrcA = 1;
        ALUSrcB = 0;

        // left_shift3: 测试左移逻辑操作，ALUSrcA=0, ALUSrcB=1
        #50;
        ReadData1 = 32'd1;
        ReadData2 = 32'd2;
        Ext = 32'd2;
        Sa = 5'b00100;
        ALUop = 3'b010;
        ALUSrcA = 0;
        ALUSrcB = 1;

        // left_shift4: 测试左移逻辑操作，ALUSrcA=1, ALUSrcB=1
        #50;
        ReadData1 = 32'd1;
        ReadData2 = 32'd2;
        Ext = 32'd2;
        Sa = 5'b00100;
        ALUop = 3'b010;
        ALUSrcA = 1;
        ALUSrcB = 1;

        // or1: 测试或运算，ALUSrcA=0, ALUSrcB=0
        #50;
        ReadData1 = 32'd1;
        ReadData2 = 32'd2;
        Ext = 32'd2;
        Sa = 5'b00100;
        ALUop = 3'b011;
        ALUSrcA = 0;
        ALUSrcB = 0;

        // or2: 测试或运算，ALUSrcA=1, ALUSrcB=0
        #50;
        ReadData1 = 32'd1;
        ReadData2 = 32'd2;
        Ext = 32'd2;
        Sa = 5'b00100;
        ALUop = 3'b011;
        ALUSrcA = 1;
        ALUSrcB = 0;

        // or3: 测试或运算，ALUSrcA=0, ALUSrcB=1
        #50;
        ReadData1 = 32'd1;
        ReadData2 = 32'd2;
        Ext = 32'd2;
        Sa = 5'b00100;
        ALUop = 3'b011;
        ALUSrcA = 0;
        ALUSrcB = 1;

        // or4: 测试或运算，ALUSrcA=1, ALUSrcB=1
        #50;
        ReadData1 = 32'd1;
        ReadData2 = 32'd2;
        Ext = 32'd2;
        Sa = 5'b00100;
        ALUop = 3'b011;
        ALUSrcA = 1;
        ALUSrcB = 1;

        // and1: 测试与运算，ALUSrcA=0, ALUSrcB=0
        #50;
        ReadData1 = 32'd1;
        ReadData2 = 32'd2;
        Ext = 32'd2;
        Sa = 5'b00100;
        ALUop = 3'b100;
        ALUSrcA = 0;
        ALUSrcB = 0;

        // and2: 测试与运算，ALUSrcA=1, ALUSrcB=0
        #50;
        ReadData1 = 32'd1;
        ReadData2 = 32'd2;
        Ext = 32'd2;
        Sa = 5'b00100;
        ALUop = 3'b100;
        ALUSrcA = 1;
        ALUSrcB = 0;

        // and3: 测试与运算，ALUSrcA=0, ALUSrcB=1
        #50;
        ReadData1 = 32'd1;
        ReadData2 = 32'd2;
        Ext = 32'd2;
        Sa = 5'b00100;
        ALUop = 3'b100;
        ALUSrcA = 0;
        ALUSrcB = 1;

        // and4: 测试与运算，ALUSrcA=1, ALUSrcB=1
        #50;
        ReadData1 = 32'd1;
        ReadData2 = 32'd2;
        Ext = 32'd2;
        Sa = 5'b00100;
        ALUop = 3'b100;
        ALUSrcA = 1;
        ALUSrcB = 1;

        // 不带符号比较1: 测试无符号小于比较，ALUSrcA=0, ALUSrcB=0
        #50;
        ReadData1 = 32'd1;
        ReadData2 = 32'd2;
        Ext = 32'd2;
        Sa = 5'b00001;
        ALUop = 3'b101;
        ALUSrcA = 0;
        ALUSrcB = 0;

        // 不带符号比较2: 测试无符号小于比较，ALUSrcA=1, ALUSrcB=0
        #50;
        ReadData1 = 32'd1;
        ReadData2 = 32'd2;
        Ext = 32'd2;
        Sa = 5'b00001;
        ALUop = 3'b101;
        ALUSrcA = 1;
        ALUSrcB = 0;

        // 不带符号比较3: 测试无符号小于比较，ALUSrcA=0, ALUSrcB=1
        #50;
        ReadData1 = 32'd1;
        ReadData2 = 32'd2;
        Ext = 32'd2;
        Sa = 5'b00001;
        ALUop = 3'b101;
        ALUSrcA = 0;
        ALUSrcB = 1;

        // 不带符号比较4: 测试无符号小于比较，ALUSrcA=1, ALUSrcB=1
        #50;
        ReadData1 = 32'd1;
        ReadData2 = 32'd2;
        Ext = 32'd2;
        Sa = 5'b00001;
        ALUop = 3'b101;
        ALUSrcA = 1;
        ALUSrcB = 1;

        // 带符号比较1: 测试带符号小于比较，ALUSrcA=0, ALUSrcB=0
        #50;
        ReadData1 = 32'd1;
        ReadData2 = 32'd2;
        Ext = 32'd2;
        Sa = 5'b00001;
        ALUop = 3'b110;
        ALUSrcA = 0;
        ALUSrcB = 0;

        // 带符号比较2: 测试带符号小于比较，ALUSrcA=1, ALUSrcB=0
        #50;
        ReadData1 = 32'd1;
        ReadData2 = 32'd2;
        Ext = 32'd2;
        Sa = 5'b00001;
        ALUop = 3'b110;
        ALUSrcA = 1;
        ALUSrcB = 0;

        // 带符号比较3: 测试带符号小于比较，ALUSrcA=0, ALUSrcB=1
        #50;
        ReadData1 = 32'd1;
        ReadData2 = 32'd2;
        Ext = 32'd2;
        Sa = 5'b00001;
        ALUop = 3'b110;
        ALUSrcA = 0;
        ALUSrcB = 1;

        // 带符号比较4: 测试带符号小于比较，ALUSrcA=1, ALUSrcB=1
        #50;
        ReadData1 = 32'd1;
        ReadData2 = 32'd2;
        Ext = 32'd2;
        Sa = 5'b00001;
        ALUop = 3'b110;
        ALUSrcA = 1;
        ALUSrcB = 1;

        // nor1: 测试异或运算，ALUSrcA=0, ALUSrcB=0
        #50;
        ReadData1 = 32'd1;
        ReadData2 = 32'd2;
        Ext = 32'd2;
        Sa = 5'b00001;
        ALUop = 3'b111;
        ALUSrcA = 0;
        ALUSrcB = 0;

        // nor2: 测试异或运算，ALUSrcA=1, ALUSrcB=0
        #50;
        ReadData1 = 32'd1;
        ReadData2 = 32'd2;
        Ext = 32'd2;
        Sa = 5'b00001;
        ALUop = 3'b111;
        ALUSrcA = 1;
        ALUSrcB = 0;

        // nor3: 测试异或运算，ALUSrcA=0, ALUSrcB=1
        #50;
        ReadData1 = 32'd1;
        ReadData2 = 32'd2;
        Ext = 32'd2;
        Sa = 5'b00001;
        ALUop = 3'b111;
        ALUSrcA = 0;
        ALUSrcB = 1;

        // nor4: 测试异或运算，ALUSrcA=1, ALUSrcB=1
        #50;
        ReadData1 = 32'd1;
        ReadData2 = 32'd2;
        Ext = 32'd2;
        Sa = 5'b00001;
        ALUop = 3'b111;
        ALUSrcA = 1;
        ALUSrcB = 1;

        // 结束仿真
        #50;
        $stop; // 停止仿真
    end

endmodule

vivado1/MyCpu单/ALU/ALU.sim/sim_1/behav/xsim/ALU32.vcd
$date
   Tue Dec  3 12:34:50 2024
$end
$version
  2019.2
$end
$timescale
  1ps
$end
$scope module ALU_sim $end
$var reg 32 ! ReadData1 [31:0] $end
$var reg 32 " ReadData2 [31:0] $end
$var reg 32 # Ext [31:0] $end
$var reg 5 $ Sa [4:0] $end
$var reg 3 % ALUop [2:0] $end
$var reg 1 & ALUSrcA $end
$var reg 1 ' ALUSrcB $end
$var wire 1 ( zero $end
$var wire 32 ) Result [31:0] $end
$scope module uut $end
$var wire 32 * ReadData1 [31:0] $end
$var wire 32 + ReadData2 [31:0] $end
$var wire 32 , Ext [31:0] $end
$var wire 5 - Sa [4:0] $end
$var wire 3 . ALUop [2:0] $end
$var wire 1 / ALUSrcA $end
$var wire 1 0 ALUSrcB $end
$var wire 1 ( zero $end
$var reg 32 1 Result [31:0] $end
$var wire 1 2 sign $end
$var wire 32 3 InA [31:0] $end
$var wire 32 4 InB [31:0] $end
$upscope $end
$upscope $end
$enddefinitions $end
#0
$dumpvars
b0 !
b0 "
b1 #
b1 $
b0 %
0&
0'
1(
b0 )
b0 *
b0 +
b1 ,
b1 -
b0 .
0/
00
b0 1
02
b0 3
b0 4
$end
#50000
b0 !
b0 "
b1 #
b1 $
b0 %
1&
0(
b1 )
1/
b1 1
b1 3
#100000
b0 !
b0 "
b1 #
b1 $
b0 %
0&
1'
0/
10
b1 1
b0 3
b1 4
#150000
b0 !
b0 "
b1 #
b1 $
b0 %
1&
b10 )
1/
b10 1
b1 3
#200000
b1 !
b10 "
b11 #
b100 $
b1 %
0&
0'
b11111111111111111111111111111111 )
b1 *
b10 +
b11 ,
b100 -
b1 .
0/
00
b11111111111111111111111111111111 1
12
b1 3
b10 4
#250000
b1 !
b10 "
b11 #
b100 $
b1 %
1&
b10 )
1/
b10 1
02
b100 3
#300000
b1 !
b10 "
b11 #
b100 $
b1 %
0&
1'
b11111111111111111111111111111110 )
0/
10
b11111111111111111111111111111110 1
12
b1 3
b11 4
#350000
b1 !
b10 "
b11 #
b100 $
b1 %
1&
b1 )
1/
b1 1
02
b100 3
#400000
b1 !
b10 "
b10 #
b100 $
b10 %
0&
0'
b100 )
b10 ,
b10 .
0/
00
b100 1
b1 3
b10 4
#450000
b1 !
b10 "
b10 #
b100 $
b10 %
1&
b100000 )
1/
b100000 1
b100 3
#500000
b1 !
b10 "
b10 #
b100 $
b10 %
0&
1'
b100 )
0/
10
b100 1
b1 3
b10 4
#550000
b1 !
b10 "
b10 #
b100 $
b10 %
1&
b100000 )
1/
b100000 1
b100 3
#600000
b1 !
b10 "
b10 #
b100 $
b11 %
0&
0'
b11 )
b11 .
0/
00
b11 1
b1 3
b10 4
#650000
b1 !
b10 "
b10 #
b100 $
b11 %
1&
b110 )
1/
b110 1
b100 3
#700000
b1 !
b10 "
b10 #
b100 $
b11 %
0&
1'
b11 )
0/
10
b11 1
b1 3
b10 4
#750000
b1 !
b10 "
b10 #
b100 $
b11 %
1&
b110 )
1/
b110 1
b100 3
#800000
b1 !
b10 "
b10 #
b100 $
b100 %
0&
0'
1(
b0 )
b100 .
0/
00
b0 1
b1 3
b10 4
#850000
b1 !
b10 "
b10 #
b100 $
b100 %
1&
1/
b0 1
b100 3
#900000
b1 !
b10 "
b10 #
b100 $
b100 %
0&
1'
0/
10
b0 1
b1 3
b10 4
#950000
b1 !
b10 "
b10 #
b100 $
b100 %
1&
1/
b0 1
b100 3
#1000000
b1 !
b10 "
b10 #
b1 $
b101 %
0&
0'
0(
b1 )
b1 -
b101 .
0/
00
b1 1
b1 3
b10 4
