vivado1/MyCpu单/ControlUnit/ControlUnit.srcs/sources_1/new/ControlUnit.v
`timescale 1ns / 1ps

module ControlUnit(
    // 根据数据通路图定义输入和输出
    input [5:0] OpCode,
    input [5:0] func,
    input zero,
    input sign,

    output PCWire,
    output ALUSrcA,
    output ALUSrcB,
    output DBDataSrc,
    output RegWire,
    output InsMemRW,
    output RD,
    output WR,
    output ExtSel,
    output RegDst,
    output [1:0] PCSrc,
    output [2:0] ALUOp
);

// 根据opcode定义控制信号为1或0
assign PCWire = (OpCode == 6'b111111) ? 0 : 1;
assign ALUSrcA = (OpCode == 6'b000000 && func == 6'b000000) ? 1 : 0;
assign ALUSrcB = (OpCode == 6'b001001 || OpCode == 6'b001100 || OpCode == 6'b001101 || OpCode == 6'b001010 || OpCode == 6'b101011 || OpCode == 6'b100011) ? 1 : 0;
assign DBDataSrc = (OpCode == 6'b100011) ? 1 : 0;
assign RegWire = (OpCode == 6'b101011 || OpCode == 6'b000100 || OpCode == 6'b000101 || OpCode == 6'b000110 || OpCode == 6'b000010) ? 0 : 1;
assign InsMemRW = 1;
assign RD = (OpCode == 6'b100011) ? 0 : 1;
assign WR = (OpCode == 6'b101011) ? 1 : 0;
assign ExtSel = (OpCode == 6'b001100 || OpCode == 6'b001101) ? 0 : 1;
assign RegDst = (OpCode == 6'b001001 || OpCode == 6'b001100 || OpCode == 6'b001101 || OpCode == 6'b001010 || OpCode == 6'b100011) ? 0 : 1;
assign PCSrc[0] = ((OpCode == 6'b000100 && zero == 1) || (OpCode == 6'b000101 && zero == 0) || (OpCode == 6'b000110 && sign == 1)) ? 1 : 0;
assign PCSrc[1] = (OpCode == 6'b000010) ? 1 : 0;
assign ALUOp[2] = (OpCode == 6'b001100 || (OpCode == 6'b000000 && func == 6'b100100) || OpCode == 6'b001010) ? 1 : 0;
assign ALUOp[1] = (OpCode == 6'b001101 || OpCode == 6'b001010 || (OpCode == 6'b000000 && func == 6'b100101) || (OpCode == 6'b000000 && func == 6'b000000)) ? 1 : 0;
assign ALUOp[0] = ((OpCode == 6'b000000 && func == 6'b100010) || OpCode == 6'b001101 || (OpCode == 6'b000000 && func == 6'b100101) || OpCode == 6'b000100 || OpCode == 6'b000101 || OpCode == 6'b000110) ? 1 : 0;

endmodule

vivado1/MyCpu单/ControlUnit/ControlUnit.srcs/sim_1/new/ControlUnit_sim.v
`timescale 1ns / 1ps
module ControlUnit_sim();

  // Input signals
  reg [5:0] OpCode;
  reg [5:0] func;
  reg zero;
  reg sign;

  // Output signals
  wire PCWire, ALUSrcA, ALUSrcB, DBDataSrc, RegWire, InsMemRW, RD, WR, RegDst, ExtSel;
  wire [1:0] PCSrc;
  wire [2:0] ALUOp;

  // Instantiate the Unit Under Test (UUT)
  ControlUnit uut (
    .OpCode(OpCode),
    .func(func),
    .zero(zero),
    .sign(sign),
    .PCWire(PCWire),
    .ALUSrcA(ALUSrcA),
    .ALUSrcB(ALUSrcB),
    .DBDataSrc(DBDataSrc),
    .RegWire(RegWire),
    .InsMemRW(InsMemRW),
    .RD(RD),
    .WR(WR),
    .RegDst(RegDst),
    .ExtSel(ExtSel),
    .PCSrc(PCSrc),
    .ALUOp(ALUOp)
  );

  // Testbench
  initial begin
    // Record waveforms
    $dumpfile("ControlUnit16.vcd");
    $dumpvars(0, ControlUnit_sim);

    // Initialize signals
    zero = 1'b0;
    sign = 1'b0;

    // Test Case 1: ADD (R-type)
    OpCode = 6'b000000;
    func = 6'b100000;  // ADD
    #50;
    
    OpCode = 6'b000000;
    func = 6'b100010;  // SUB
    #50;
    
    OpCode = 6'b001001;
    func = 6'bxxxxxx;  // ADDIU
    #50;
    
    OpCode = 6'b001100;
    func = 6'bxxxxxx;  // ANDI
    #50;
    
    OpCode = 6'b000000;
    func = 6'b100100;  // AND
    #50;
    
    OpCode = 6'b001101;
    func = 6'bxxxxxx;  // ORI
    #50;
  
    OpCode = 6'b000000;
    func = 6'b100101;  // OR
    #50;
    
    OpCode = 6'b000000;
    func = 6'b000000;  // SLL
    #50;    

    OpCode = 6'b001010;
    func = 6'bxxxxxx;  // SLTI
    #50;
    
    OpCode = 6'b101011;
    func = 6'bxxxxxx;  // SW
    #50;
    
    OpCode = 6'b100011;
    func = 6'bxxxxxx;  // LW
    #50;
    
    OpCode = 6'b000100;
    func = 6'bxxxxxx;  // BEQ
    zero = 1'b1;
    #50;
    
    OpCode = 6'b000101;
    func = 6'bxxxxxx;  // BNE
    zero = 1'b0;
    #50;
    
    OpCode = 6'b000110;
    func = 6'bxxxxxx;  // BLEZ
    sign = 1'b1;
    #50;
    
    OpCode = 6'b000010;
    func = 6'bxxxxxx;  // J
    #50;
    
    OpCode = 6'b111111;
    func = 6'bxxxxxx;  // HALT
    #50;
    $stop;
    end
    endmodule

vivado1/MyCpu单/ControlUnit/ControlUnit.sim/sim_1/behav/xsim/ControlUnit16.vcd
$date
   Tue Dec  3 12:35:54 2024
$end
$version
  2019.2
$end
$timescale
  1ps
$end
$scope module ControlUnit_sim $end
$var reg 6 ! OpCode [5:0] $end
$var reg 6 " func [5:0] $end
$var reg 1 # zero $end
$var reg 1 $ sign $end
$var wire 1 % PCWire $end
$var wire 1 & ALUSrcA $end
$var wire 1 ' ALUSrcB $end
$var wire 1 ( DBDataSrc $end
$var wire 1 ) RegWire $end
$var wire 1 * InsMemRW $end
$var wire 1 + RD $end
$var wire 1 , WR $end
$var wire 1 - RegDst $end
$var wire 1 . ExtSel $end
$var wire 2 / PCSrc [1:0] $end
$var wire 3 0 ALUOp [2:0] $end
$scope module uut $end
$var wire 6 1 OpCode [5:0] $end
$var wire 6 2 func [5:0] $end
$var wire 1 3 zero $end
$var wire 1 4 sign $end
$var wire 1 % PCWire $end
$var wire 1 & ALUSrcA $end
$var wire 1 ' ALUSrcB $end
$var wire 1 ( DBDataSrc $end
$var wire 1 ) RegWire $end
$var wire 1 * InsMemRW $end
$var wire 1 + RD $end
$var wire 1 , WR $end
$var wire 1 . ExtSel $end
$var wire 1 - RegDst $end
$var wire 2 / PCSrc [1:0] $end
$var wire 3 0 ALUOp [2:0] $end
$upscope $end
$upscope $end
$enddefinitions $end
#0
$dumpvars
b0 !
b100000 "
0#
0$
1%
0&
0'
0(
1)
1*
1+
0,
1-
1.
b0 /
b0 0
b0 1
b100000 2
03
04
$end
#50000
b0 !
b100010 "
b1 0
b100010 2
#100000
b1001 !
bx "
1'
0-
b0 0
b1001 1
bx 2
#150000
b1100 !
bx "
0.
b100 0
b1100 1
#200000
b0 !
b100100 "
0'
1-
1.
b0 1
b100100 2
#250000
b1101 !
bx "
1'
0-
0.
b11 0
b1101 1
bx 2
#300000
b0 !
b100101 "
0'
1-
1.
b0 1
b100101 2
#350000
b0 !
b0 "
1&
b10 0
b0 2
#400000
b1010 !
bx "
0&
1'
0-
b110 0
b1010 1
bx 2
#450000
b101011 !
bx "
0)
1,
1-
b0 0
b101011 1
#500000
b100011 !
bx "
1(
1)
0+
0,
0-
b100011 1
#550000
b100 !
bx "
1#
0'
0(
0)
1+
1-
b1 /
b1 0
b100 1
13
#600000
b101 !
bx "
0#
b101 1
03
#650000
b110 !
bx "
1$
b110 1
14
#700000
b10 !
bx "
b10 /
b0 0
b10 1
#750000
b111111 !
bx "
0%
1)
b0 /
b111111 1
