vivado1/MyCpu单/PC/PC.srcs/sources_1/new/PC.v
`timescale 1ns / 1ps

module PC(
    input CLK, // 时钟信号
    input Reset, // 复位信号：当为低电平时将PC置零
    input PCWre, // 写使能信号：为高电平时允许更新PC值
    input [1:0] PCSrc, // 程序计数器源选择信号
    input signed [15:0] Immediate, // 立即数
    input [31:0] JumpPC, // 跳转目标地址

    output reg signed [31:0] Address, // 当前的PC值
    output [31:0] nextPC, // 下一个PC值
    output [3:0] PC4 // 当前PC值的高4位
);

// 计算下一个PC值
// 如果PCSrc[0]为1，则执行相对跳转：Address + 4 + (Immediate << 2)
// 如果PCSrc[1]为1，则执行绝对跳转：JumpPC
// 否则顺序执行下一条指令：Address + 4
assign nextPC = (PCSrc[0]) ? Address + 4 + (Immediate << 2) : ((PCSrc[1]) ? JumpPC : Address + 4);

// 提取当前PC值的高4位
assign PC4 = Address[31:28];

// 在CLK或Reset的下降沿触发
always @(negedge CLK or negedge Reset) begin
    if(Reset == 0) begin
        // 如果Reset为低电平，将PC置零
        Address = 0;
    end else if(PCWre) begin // 只有在PCWre为高电平时才允许更改PC值
        if(PCSrc[0]) begin
            // 如果PCSrc[0]为1，执行相对跳转
            Address = Address + 4 + (Immediate << 2);
        end else if(PCSrc[1]) begin
            // 如果PCSrc[1]为1，执行绝对跳转
            Address = JumpPC;
        end else begin
            // 否则，顺序执行下一条指令
            Address = Address + 4;
        end
    end
end

endmodule

vivado1/MyCpu单/PC/PC.srcs/sim_1/new/PC_sim.v
`timescale 1ns / 1ps

module PC_sim();

    // 定义输入信号为寄存器类型
    reg CLK;                     // 时钟信号
    reg Reset;                   // 复位信号
    reg PCWre;                   // 写使能信号
    reg [1:0] PCSrc;             // 程序计数器源选择信号，2位
    reg signed [15:0] Immediate;  // 符号扩展的立即数
    reg [31:0] JumpPC;           // 添加缺失的JumpPC信号

    // 定义输出信号为线网类型
    wire [31:0] Address;         // 当前的PC值

    // 实例化 PC 模块，并连接端口
    PC uut (
        .CLK(CLK),
        .Reset(Reset),
        .PCWre(PCWre),
        .PCSrc(PCSrc),           // 2位信号
        .Immediate(Immediate),
        .JumpPC(JumpPC),         // 连接JumpPC信号
        .Address(Address)
    );

    // 生成时钟信号，每15个时间单位翻转一次
    always #7.5 CLK = !CLK;      // 使用更精确的时间单位（半个周期为7.5ns）

    initial begin
        // 设置波形记录文件
        $dumpfile("PC.vcd"); // 波形文件名
        $dumpvars(0, PC_sim); // 记录所有变量

        // 初始化
        CLK = 0;
        Reset = 0;
        PCWre = 0;
        PCSrc = 2'b00;          // 初始化为顺序执行
        Immediate = 0;
        JumpPC = 32'h0000_0000; // 初始化JumpPC为0

        // 不跳转，顺序执行下一条地址
        #100;                   // 延迟100个时间单位
        Reset = 1;              // 取消复位
        PCWre = 1;              // 允许更新PC值
        PCSrc = 2'b00;          // 顺序执行
        Immediate = 4;          // 设置立即数


        // 跳转，执行跳转之后的指令
        #100;
        PCSrc = 2'b01;          // 相对跳转
        Immediate = 4;


        // 绝对跳转，执行跳转之后的指令
        #100;
        PCSrc = 2'b10;          // 绝对跳转
        JumpPC = 32'h0000_1000; // 设置跳转地址

        // 结束仿真
        #100;
        $stop;                  // 停止仿真
    end

endmodule

vivado1/MyCpu单/PC/PC.sim/sim_1/behav/xsim/PC.vcd
$date
   Wed Dec  4 19:23:43 2024
$end
$version
  2019.2
$end
$timescale
  1ps
$end
$scope module PC_sim $end
$var reg 1 ! CLK $end
$var reg 1 " Reset $end
$var reg 1 # PCWre $end
$var reg 2 $ PCSrc [1:0] $end
$var reg 16 % Immediate [15:0] $end
$var reg 32 & JumpPC [31:0] $end
$var wire 32 ' Address [31:0] $end
$scope module uut $end
$var wire 1 ( CLK $end
$var wire 1 ) Reset $end
$var wire 1 * PCWre $end
$var wire 2 + PCSrc [1:0] $end
$var wire 16 , Immediate [15:0] $end
$var wire 32 - JumpPC [31:0] $end
$var reg 32 . Address [31:0] $end
$var wire 32 / nextPC [31:0] $end
$var wire 4 0 PC4 [3:0] $end
$upscope $end
$upscope $end
$enddefinitions $end
#0
$dumpvars
0!
0"
0#
b0 $
b0 %
b0 &
b0 '
0(
0)
0*
b0 +
b0 ,
b0 -
b0 .
b100 /
b0 0
$end
#7500
1!
1(
#15000
0!
0(
b0 .
#22500
1!
1(
#30000
0!
0(
b0 .
#37500
1!
1(
#45000
0!
0(
b0 .
#52500
1!
1(
#60000
0!
0(
b0 .
#67500
1!
1(
#75000
0!
0(
b0 .
#82500
1!
1(
#90000
0!
0(
b0 .
#97500
1!
1(
#100000
1"
1#
b0 $
b100 %
1)
1*
b100 ,
#105000
0!
b100 '
0(
b100 .
b1000 /
#112500
1!
1(
#120000
0!
b1000 '
0(
b1000 .
b1100 /
#127500
1!
1(
#135000
0!
b1100 '
0(
b1100 .
b10000 /
#142500
1!
1(
#150000
0!
b10000 '
0(
b10000 .
b10100 /
#157500
1!
1(
#165000
0!
b10100 '
0(
b10100 .
b11000 /
#172500
1!
1(
#180000
0!
b11000 '
0(
b11000 .
b11100 /
#187500
1!
1(
#195000
0!
b11100 '
0(
b11100 .
b100000 /
#200000
b1 $
b100 %
b1 +
b110000 /
#202500
1!
1(
#210000
0!
b110000 '
0(
b110000 .
b1000100 /
#217500
1!
1(
#225000
0!
b1000100 '
0(
b1000100 .
b1011000 /
#232500
1!
1(
#240000
0!
b1011000 '
0(
b1011000 .
b1101100 /
#247500
1!
1(
#255000
0!
b1101100 '
0(
b1101100 .
b10000000 /
#262500
1!
1(
#270000
0!
b10000000 '
0(
b10000000 .
b10010100 /
#277500
1!
1(
#285000
0!
b10010100 '
0(
b10010100 .
b10101000 /
#292500
1!
1(
#300000
0!
b10 $
b1000000000000 &
b1000000000000 '
0(
b10 +
b1000000000000 -
b1000000000000 .
b1000000000000 /
#307500
1!
1(
#315000
0!
0(
b1000000000000 .
#322500
1!
1(
#330000
0!
0(
b1000000000000 .
#337500
1!
1(
#345000
0!
0(
b1000000000000 .
#352500
1!
1(
#360000
0!
0(
b1000000000000 .
#367500
1!
1(
#375000
0!
0(
b1000000000000 .
#382500
1!
1(
#390000
0!
0(
b1000000000000 .
