vivado1/MyCpu单/SingleCycleCPU/SingleCycleCPU.srcs/sources_1/new/SignZeroExtend.v
`timescale 1ns / 1ps
module SignZeroExtend(
    // 根据数据通路定义输入和输出
    input wire [15:0] Immediate,  // 输入的16位立即数
    input ExtSel,                // 扩展选择信号：1为符号扩展，0为零扩展
    output wire [31:0] Out       // 输出的32位扩展后的数据
);

// 后16位存储立即数
// 直接将输入的16位立即数赋值给输出的低16位
assign Out[15:0] = Immediate[15:0];

// 前16位根据立即数进行补1或补0的操作
// 如果 ExtSel 为1，则进行符号扩展：将 Immediate 的最高位（第15位）复制到高16位
// 如果 ExtSel 为0，则进行零扩展：将高16位全部设为0
assign Out[31:16] = ExtSel == 1 ? {16{Immediate[15]}} : 16'b0;

endmodule

vivado1/MyCpu单/RegisterFile/RegisterFile.srcs/sources_1/new/RegisterFile.v
`timescale 1ns / 1ps
module RegisterFile(
    input CLK,                   // 时钟信号
    input RegDst,                // 寄存器目标选择信号：为1时选择rd，为0时选择rt
    input RegWre,                // 寄存器写使能信号：为1时允许写入寄存器
    input DBDataSrc,             // 数据源选择信号：为1时从数据存储器读取，为0时从ALU读取

    // input [5:0] Opcode,        // 指令操作码（注释掉）
    input [4:0] rs,              // 源寄存器1编号
    input [4:0] rt,              // 源寄存器2编号
    input [4:0] rd,              // 目标寄存器编号

    // input [10:0] im,           // 立即数（注释掉）

    input [31:0] dataFromALU,    // 来自ALU的数据
    input [31:0] dataFromRW,     // 来自数据存储器或其它源的数据

    output [31:0] Data1,         // ALU运算的第一个输入A
    output [31:0] Data2,         // ALU运算的第二个输入B
    output [31:0] writeData      // 写入寄存器的数据
);

// 要写的寄存器端口
wire [4:0] writeReg;

// 根据 RegDst 选择要写入的目标寄存器
// RegDst 为真时，处理R型指令，使用 rd 作为目标寄存器；为假时，处理I型指令，使用 rt 作为目标寄存器
assign writeReg = RegDst ? rd : rt;

// 根据 DBDataSrc 选择写入寄存器的数据来源
// DBDataSrc 为0时，使用来自ALU的输出；为1时，使用来自数据存储器的输出
assign writeData = DBDataSrc ? dataFromRW : dataFromALU;

// 初始化寄存器数组，共32个32位寄存器
reg [31:0] register[0:31];
integer i;
initial begin
    for(i = 0; i < 32; i = i + 1) 
        register[i] <= 0; // 所有寄存器初始值设为0
end

// 输出 Data1 和 Data2 随寄存器变化而变化
// Data1 为 ALU 运算时的第一个输入 A，其值始终为 rs 寄存器的内容
// Data2 为 ALU 运算时的第二个输入 B，其值始终为 rt 寄存器的内容
// 注意：原始代码中关于 Opcode 的条件已经注释掉了，这里不再考虑 sll 指令的情况
assign Data1 = register[rs];
assign Data2 = register[rt];

// 在时钟下降沿触发，更新寄存器内容
always @ (negedge CLK) begin
    if(RegWre && writeReg != 0) // 只有在 RegWre 为高电平且不是写入0号寄存器时才允许写入
        register[writeReg] <= writeData;
end

endmodule

vivado1/MyCpu单/InstructionMemory/InstructionMemory.srcs/sources_1/new/InstructionMemory.v
`timescale 1ns / 1ps
module InstructionMemory(
    input [3:0] PC4, // 用于跳转指令的高4位PC值
    input [31:0] IAddr, // 指令地址输入
    input RW, // 读写控制信号：0 表示写入，1 表示读取

    output [5:0] op, // 操作码
    output [5:0] funct,
    output [4:0] rs, // 源寄存器1
    output [4:0] rt, // 源寄存器2/目标寄存器
    output [4:0] rd, // 目标寄存器（仅适用于某些指令）
    output [15:0] Immediate, // 立即数
    output [4:0] Sa, // 移位量
    output [31:0] JumpPC, // 跳转地址
    output reg [31:0] IDataOut // 用于保存从内存读取的32位指令
);

// 因为实验要求指令存储器和数据存储器单元宽度一律使用8位，
// 因此将一个32位的指令拆成4个8位的存储器单元存储。
reg [7:0] Mem[0:127]; // 定义一个8位宽、128个地址空间的内存数组来存储指令


// 将IDataOut中的相应位分配给输出端口
assign op = IDataOut[31:26]; // 提取操作码 (6位)
assign rs = IDataOut[25:21]; // 提取源寄存器1 (5位)
assign rt = IDataOut[20:16]; // 提取源寄存器2或目标寄存器 (5位)
assign rd = IDataOut[15:11]; // 提取目标寄存器 (5位)
assign Immediate = IDataOut[15:0]; // 提取立即数 (16位)
assign Sa = IDataOut[10:6]; // 提取移位量 (5位)
assign funct = (IDataOut[31:26] == 6'b000000)? IDataOut[5:0] : 6'bxxxxxx;

// 构建跳转地址，由PC4和指令的一部分组成，并在末尾添加两个零以确保是字对齐的
assign JumpPC = {PC4, IDataOut[25:0], 2'b00};

initial begin
    $readmemb("C:/Users/Bamboo/Desktop/vivado1/MyCpu/Instruction.txt", Mem); // 在仿真开始时从文件 "Instructions.txt" 中加载指令集到内存
    IDataOut = 0; // 初始化指令数据为0
end

// 当IAddr或RW为1触发
always @( RW or  IAddr) begin
    if(RW == 1) begin // 如果是读操作
        // 根据IAddr从内存中读取4个连续的8位数据并组合成32位指令
        IDataOut[7:0]  = Mem[IAddr + 3];
        IDataOut[15:8] = Mem[IAddr + 2];
        IDataOut[23:16] = Mem[IAddr + 1];
        IDataOut[31:24] = Mem[IAddr];
    end
end

endmodule

vivado1/MyCpu单/SingleCycleCPU_new/SingleCycleCPU_new.srcs/sources_1/new/DataMemory.v
module DataMemory(
    input CLK, // 时钟信号
    input wire [31:0] DAddr,  // 地址输入，用于指定访问的内存位置
    input wire [31:0] DataIn, // 数据输入，当进行写操作时，此为要写入的数据
    input RD,                 // 读使能信号：为1时允许读操作，为0时不进行读操作（或高阻态）
    input WR,                 // 写使能信号：为0时允许写操作，为1时禁止写操作或输出高阻态
    output wire [31:0] DataOut // 数据输出，当进行读操作时，从此输出读取的数据
);

// 定义一个8位宽、128个地址空间的内存数组
reg [7:0] Memory [0:127]; // 每个存储单元为8位，共有128个这样的存储单元

// 因为一条指令由四个存储单元存储，所以地址需要左移两位以乘以4
wire [31:0] address;
assign address = (DAddr << 2); // 将输入地址左移两位，相当于乘以4，得到实际的字节地址

// 读操作：如果RD为1，则从内存中读取数据；否则输出高阻态（'z')
assign DataOut[7:0]  = (RD == 1) ? Memory[address + 3] : 8'bz; // 最低字节
assign DataOut[15:8] = (RD == 1) ? Memory[address + 2] : 8'bz; // 第二个字节
assign DataOut[23:16] = (RD == 1) ? Memory[address + 1] : 8'bz; // 第三个字节
assign DataOut[31:24] = (RD == 1) ? Memory[address] : 8'bz; // 最高字节

// 写操作：在CLK的下降沿触发，如果WR为0，则将DataIn中的数据写入内存
always @ (negedge CLK) begin
    if(WR == 1) begin // 如果写使能信号为0，则执行写操作
        Memory[address] <= DataIn[31:24];   // 写入最高字节
        Memory[address + 1] <= DataIn[23:16]; // 写入第三个字节
        Memory[address + 2] <= DataIn[15:8];  // 写入第二个字节
        Memory[address + 3] <= DataIn[7:0];   // 写入最低字节
    end
end
 
endmodule

vivado1/MyCpu单/SingleCycleCPU_new - 副本/SingleCycleCPU_new.srcs/sources_1/new/ControlUnit.v
`timescale 1ns / 1ps

module ControlUnit(
    // 根据数据通路图定义输入和输出
    input [5:0] OpCode,
    input [5:0] func,
    input zero,
    input sign,

    output PCWire,
    output ALUSrcA,
    output ALUSrcB,
    output DBDataSrc,
    output RegWire,
    output InsMemRW,
    output RD,
    output WR,
    output ExtSel,
    output RegDst,
    output [1:0] PCSrc,
    output [2:0] ALUOp
);

// 根据opcode定义控制信号为1或0
assign PCWire = (OpCode == 6'b111111) ? 0 : 1;
assign ALUSrcA = (OpCode == 6'b000000 && func == 6'b000000) ? 1 : 0;
assign ALUSrcB = (OpCode == 6'b001001 || OpCode == 6'b001100 || OpCode == 6'b001101 || OpCode == 6'b001010 || OpCode == 6'b101011 || OpCode == 6'b100011) ? 1 : 0;
assign DBDataSrc = (OpCode == 6'b100011) ? 1 : 0;
assign RegWire = (OpCode == 6'b101011 || OpCode == 6'b000100 || OpCode == 6'b000101 || OpCode == 6'b000110 || OpCode == 6'b000010) ? 0 : 1;
assign InsMemRW = 1;
assign RD = (OpCode == 6'b100011) ? 1 : 0;
assign WR = (OpCode == 6'b101011) ? 1 : 0;
assign ExtSel = (OpCode == 6'b001100 || OpCode == 6'b001101) ? 0 : 1;
assign RegDst = (OpCode == 6'b001001 || OpCode == 6'b001100 || OpCode == 6'b001101 || OpCode == 6'b001010 || OpCode == 6'b100011) ? 0 : 1;
assign PCSrc[0] = ((OpCode == 6'b000100 && zero == 1) || (OpCode == 6'b000101 && zero == 0) || (OpCode == 6'b000110 && sign == 1)) ? 1 : 0;
assign PCSrc[1] = (OpCode == 6'b000010) ? 1 : 0;
assign ALUOp[2] = (OpCode == 6'b001100 || (OpCode == 6'b000000 && func == 6'b100100) || OpCode == 6'b001010) ? 1 : 0;
assign ALUOp[1] = (OpCode == 6'b001101 || OpCode == 6'b001010 || (OpCode == 6'b000000 && func == 6'b100101) || (OpCode == 6'b000000 && func == 6'b000000)) ? 1 : 0;
assign ALUOp[0] = ((OpCode == 6'b000000 && func == 6'b100010) || OpCode == 6'b001101 || (OpCode == 6'b000000 && func == 6'b100101) || OpCode == 6'b000100 || OpCode == 6'b000101 || OpCode == 6'b000110) ? 1 : 0;

endmodule

vivado1/MyCpu单/SingleCycleCPU_new - 副本/SingleCycleCPU_new.srcs/sources_1/new/PC.v
`timescale 1ns / 1ps

module PC(
    input CLK, // 时钟信号
    input Reset, // 复位信号：当为低电平时将PC置零
    input PCWre, // 写使能信号：为高电平时允许更新PC值
    input [1:0] PCSrc, // 程序计数器源选择信号
    input signed [15:0] Immediate, // 立即数
    input [31:0] JumpPC, // 跳转目标地址

    output reg signed [31:0] Address, // 当前的PC值
    output [31:0] nextPC, // 下一个PC值
    output [3:0] PC4 // 当前PC值的高4位
);

// 计算下一个PC值
// 如果PCSrc[0]为1，则执行相对跳转：Address + 4 + (Immediate << 2)
// 如果PCSrc[1]为1，则执行绝对跳转：JumpPC
// 否则顺序执行下一条指令：Address + 4
assign nextPC = (PCSrc[0]) ? Address + 4 + (Immediate << 2) : ((PCSrc[1]) ? JumpPC : Address + 4);

// 提取当前PC值的高4位
assign PC4 = Address[31:28];

// 在CLK或Reset的下降沿触发
always @(posedge CLK or negedge Reset) begin
    if(Reset == 0) begin
        // 如果Reset为低电平，将PC置零
        Address = 0;
    end else if(PCWre) begin // 只有在PCWre为高电平时才允许更改PC值
        if(PCSrc[0]) begin
            // 如果PCSrc[0]为1，执行相对跳转
            Address = Address + 4 + (Immediate << 2);
        end else if(PCSrc[1]) begin
            // 如果PCSrc[1]为1，执行绝对跳转
            Address = JumpPC;
        end else begin
            // 否则，顺序执行下一条指令
            Address = Address + 4;
        end
    end
end

endmodule

vivado1/MyCpu单/SingleCycleCPU_new - 副本/SingleCycleCPU_new.srcs/sources_1/new/ALU.v
`timescale 1ns / 1ps
module ALU(
    // 定义ALU模块的输入和输出端口
    input [31:0] ReadData1,      // 第一个操作数，来自寄存器文件
    input [31:0] ReadData2,      // 第二个操作数，来自寄存器文件
    input [31:0] Ext,            // 扩展后的立即数（用于某些指令）
    input [4:0] Sa,              // 移位量（通常由shamt字段提供）
    input [2:0] ALUop,           // 指定要执行的操作类型
    input ALUSrcA,               // 控制信号：选择InA的来源（ReadData1或Sa）
    input ALUSrcB,               // 控制信号：选择InB的来源（ReadData2或Ext）

    output wire zero,            // 输出信号：当Result为0时置1
    output reg [31:0] Result,     // 运算结果输出
    output wire sign              //符号
);

    // 内部连接线，用于表示实际参与运算的操作数
    wire [31:0] InA;             // 实际参与运算的第一个操作数
    wire [31:0] InB;             // 实际参与运算的第二个操作数

    // 根据控制信号ALUSrcA选择InA的来源：
    // 如果ALUSrcA为1，则InA = {27'b0, Sa}（即高27位为0，低5位为Sa）
    // 否则，InA = ReadData1
    assign InA = ALUSrcA ? {{27{1'b0}}, Sa} : ReadData1;

    // 根据控制信号ALUSrcB选择InB的来源：
    // 如果ALUSrcB为1，则InB = Ext（扩展后的立即数）
    // 否则，InB = ReadData2
    assign InB = ALUSrcB ? Ext : ReadData2;

    // 计算零标志位zero：如果Result为全0，则zero置1；否则为0
    assign zero = (Result == 32'b0) ? 1 : 0;
    assign sign = Result[31];
    // 组合逻辑块，当任何输入发生变化时自动重新计算Result
    always @(*) begin
        case(ALUop) // 根据ALUop的值选择执行不同的运算功能
            3'b000 : 
                Result = InA + InB;                    // 加法操作
            3'b001:
                Result = InA - InB;                    // 减法操作
            3'b010:
                Result = InB << InA[4:0];              // 左移逻辑操作（使用Sa的低5位作为移位数量）
            3'b011:
                Result = InA | InB;                    // 或运算
            3'b100:
                Result = InA & InB;                    // 与运算
            3'b101:
                Result = (InA < InB) ? 32'b1 : 32'b0; // 无符号小于比较（返回32位的1或0）
            3'b110: 
                Result = (((InA < InB) && (InA[31] == InB[31])) || 
                          ((InA[31] == 1'b1) && (InB[31] == 1'b0))) ? 32'b1 : 32'b0; // 带符号小于比较
            3'b111:
                Result = InA ^ InB;                    // 异或运算
            default:
                Result = 32'h00000000;                 // 默认情况，将Result清零
        endcase
    end

endmodule

vivado1/MyCpu单/SingleCycleCPU/SingleCycleCPU.srcs/sources_1/new/SingleCycleCPU.v
`timescale 1ns / 1ps

module SingleCycleCPU(
    input CLK, Reset,
    output [4:0] rs, rt,
    output wire [5:0] Opcode,
    output wire [31:0] Out1, Out2, curPC, nextPC, Result, DBData, Instruction
);

    wire [2:0] ALUOp;
    wire [5:0] func;
    wire [31:0] Extout, DMOut;
    wire [15:0] Immediate;
    wire [4:0] rd;
    wire [4:0] sa;
    wire [31:0] JumpPC;
    wire zero, sign, PCWire, ALUSrcA, ALUSrcB, DBDataSrc, ReWire;
    wire InsMemRW, RD, WR, ExtSel, RegDst;
    wire [1:0] PCSrc;
    wire [3:0] PC4;

    ALU alu(Out1, Out2, Extout, sa, ALUOp, ALUSrcA, ALUSrcB, zero, Result, sign);
    PC pc(CLK, Reset, PCWire, PCSrc, Immediate, JumpPC, curPC, nextPC, PC4);
    ControlUnit CU(Opcode, func, zero, sign, PCWire, ALUSrcA, ALUSrcB, DBDataSrc, ReWire, InsMemRW, RD, WR, ExtSel, RegDst, PCSrc, ALUOp);
    DataMemory DM(CLK, Result, Out2, RD, WR, DMOut);
    InstructionMemory IM(PC4, curPC, InsMemRW, Opcode, func, rs, rt, rd, Immediate, sa, JumpPC, Instruction);
    RegisterFile RF(CLK, RegDst, ReWire, DBDataSrc, rs, rt, rd, Result, DMOut, Out1, Out2, DBData);
    SignZeroExtend SZE(Immediate, ExtSel, Extout);

endmodule

vivado1/MyCpu单/SingleCycleCPU_new/SingleCycleCPU_new.srcs/sim_1/new/SingleCycleCPU_sim.v
`timescale 1ns / 1ps

module SingleCycleCPU_sim();

    //inputs
    reg CLK;
    reg Reset;

    //Outputs
    wire [31:0] Out1;
    wire [31:0] Out2;
    wire [31:0] curPC;
    wire [31:0] Result;
    wire [5:0] Opcode;

    //instantiate the Unit Under Test
    SingleCycleCPU uut(
        .CLK(CLK),
        .Reset(Reset),
        .Opcode(Opcode),
        .Out1(Out1),
        .Out2(Out2),
        .curPC(curPC),
        .Result(Result)
    );

    initial begin 
        //record 
        $dumpfile("SCCPU.vcd");
        $dumpvars(0, SingleCycleCPU_sim);

        //innitial inputs
        CLK = 0;
        Reset = 0;//刚开始设置PC为0

        #50;
        CLK = 1;

        #50;
        Reset = 1;

        //产生时钟信号
        forever #50 begin
            CLK = !CLK;
        end

    

    end

endmodule

vivado1/MyCpu单/SingleCycleCPU_new - 副本/SingleCycleCPU_new.sim/sim_1/behav/xsim/SCCPU.vcd
$date
   Wed Dec  4 09:54:39 2024
$end
$version
  2019.2
$end
$timescale
  1ps
$end
$scope module SingleCycleCPU_sim $end
$var reg 1 ! CLK $end
$var reg 1 " Reset $end
$var wire 32 # Out1 [31:0] $end
$var wire 32 $ Out2 [31:0] $end
$var wire 32 % curPC [31:0] $end
$var wire 32 & Result [31:0] $end
$var wire 6 ' Opcode [5:0] $end
$scope module uut $end
$var wire 1 ( CLK $end
$var wire 1 ) Reset $end
$var wire 5 * rs [4:0] $end
$var wire 5 + rt [4:0] $end
$var wire 6 ' Opcode [5:0] $end
$var wire 32 # Out1 [31:0] $end
$var wire 32 $ Out2 [31:0] $end
$var wire 32 % curPC [31:0] $end
$var wire 32 , nextPC [31:0] $end
$var wire 32 & Result [31:0] $end
$var wire 32 - DBData [31:0] $end
$var wire 32 . Instruction [31:0] $end
$var wire 3 / ALUOp [2:0] $end
$var wire 6 0 func [5:0] $end
$var wire 32 1 Extout [31:0] $end
$var wire 32 2 DMOut [31:0] $end
$var wire 16 3 Immediate [15:0] $end
$var wire 5 4 rd [4:0] $end
$var wire 5 5 sa [4:0] $end
$var wire 32 6 JumpPC [31:0] $end
$var wire 1 7 zero $end
$var wire 1 8 sign $end
$var wire 1 9 PCWire $end
$var wire 1 : ALUSrcA $end
$var wire 1 ; ALUSrcB $end
$var wire 1 < DBDataSrc $end
$var wire 1 = ReWire $end
$var wire 1 > InsMemRW $end
$var wire 1 ? RD $end
$var wire 1 @ WR $end
$var wire 1 A ExtSel $end
$var wire 1 B RegDst $end
$var wire 2 C PCSrc [1:0] $end
$var wire 4 D PC4 [3:0] $end
$scope module alu $end
$var wire 32 # ReadData1 [31:0] $end
$var wire 32 $ ReadData2 [31:0] $end
$var wire 32 1 Ext [31:0] $end
$var wire 5 5 Sa [4:0] $end
$var wire 3 / ALUop [2:0] $end
$var wire 1 : ALUSrcA $end
$var wire 1 ; ALUSrcB $end
$var wire 1 7 zero $end
$var reg 32 E Result [31:0] $end
$var wire 1 8 sign $end
$var wire 32 F InA [31:0] $end
$var wire 32 G InB [31:0] $end
$upscope $end
$scope module pc $end
$var wire 1 ( CLK $end
$var wire 1 ) Reset $end
$var wire 1 9 PCWre $end
$var wire 2 C PCSrc [1:0] $end
$var wire 16 3 Immediate [15:0] $end
$var wire 32 6 JumpPC [31:0] $end
$var reg 32 H Address [31:0] $end
$var wire 32 , nextPC [31:0] $end
$var wire 4 D PC4 [3:0] $end
$upscope $end
$scope module CU $end
$var wire 6 ' OpCode [5:0] $end
$var wire 6 0 func [5:0] $end
$var wire 1 7 zero $end
$var wire 1 8 sign $end
$var wire 1 9 PCWire $end
$var wire 1 : ALUSrcA $end
$var wire 1 ; ALUSrcB $end
$var wire 1 < DBDataSrc $end
$var wire 1 = RegWire $end
$var wire 1 > InsMemRW $end
$var wire 1 ? RD $end
$var wire 1 @ WR $end
$var wire 1 A ExtSel $end
$var wire 1 B RegDst $end
$var wire 2 C PCSrc [1:0] $end
$var wire 3 / ALUOp [2:0] $end
$upscope $end
$scope module DM $end
$var wire 1 ( CLK $end
$var wire 32 & DAddr [31:0] $end
$var wire 32 $ DataIn [31:0] $end
$var wire 1 ? RD $end
$var wire 1 @ WR $end
$var wire 32 2 DataOut [31:0] $end
$var wire 32 I address [31:0] $end
$upscope $end
$scope module IM $end
$var wire 4 D PC4 [3:0] $end
$var wire 32 % IAddr [31:0] $end
$var wire 1 > RW $end
$var wire 6 ' op [5:0] $end
$var wire 6 0 funct [5:0] $end
$var wire 5 * rs [4:0] $end
$var wire 5 + rt [4:0] $end
$var wire 5 4 rd [4:0] $end
$var wire 16 3 Immediate [15:0] $end
$var wire 5 5 Sa [4:0] $end
$var wire 32 6 JumpPC [31:0] $end
$var reg 32 J IDataOut [31:0] $end
$upscope $end
$scope module RF $end
$var wire 1 ( CLK $end
$var wire 1 B RegDst $end
$var wire 1 = RegWre $end
$var wire 1 < DBDataSrc $end
$var wire 5 * rs [4:0] $end
$var wire 5 + rt [4:0] $end
$var wire 5 4 rd [4:0] $end
$var wire 32 & dataFromALU [31:0] $end
$var wire 32 2 dataFromRW [31:0] $end
$var wire 32 # Data1 [31:0] $end
$var wire 32 $ Data2 [31:0] $end
$var wire 32 - writeData [31:0] $end
$var wire 5 K writeReg [4:0] $end
$var integer 32 L i $end
$upscope $end
$scope module SZE $end
$var wire 16 3 Immediate [15:0] $end
$var wire 1 A ExtSel $end
$var wire 32 1 Out [31:0] $end
$upscope $end
$upscope $end
$upscope $end
$enddefinitions $end
#0
$dumpvars
0!
0"
b0 #
b0 $
b0 %
b1000 &
b1001 '
0(
0)
b0 *
b1 +
b100 ,
b1000 -
b100100000000010000000000001000 .
b0 /
bx 0
b1000 1
bz 2
b1000 3
b0 4
b0 5
b1000000000000100000 6
07
08
19
0:
1;
0<
1=
1>
0?
0@
1A
0B
b0 C
b0 D
b1000 E
b0 F
b1000 G
b0 H
b100000 I
b100100000000010000000000001000 J
b1 K
b100000 L
$end
#50000
1!
1(
b0 H
#100000
1"
1)
#150000
0!
b0 #
b1000 $
0(
b1000 G
#200000
1!
b0 $
b100 %
b10 &
b1101 '
1(
b10 +
b1000 ,
b10 -
b110100000000100000000000000010 .
b11 /
bx 0
b10 1
bz 2
b10 3
b10000000000000001000 6
07
0:
1;
0<
0?
0A
0B
b0 C
b10 E
b10 G
b100 H
b1000 I
b110100000000100000000000000010 J
b10 K
#250000
0!
b0 #
b10 $
0(
b10 G
#300000
1!
b10 #
b1000 $
b1000 %
b1010 &
b0 '
1(
b10 *
b1 +
b1100 ,
b1010 -
b10000010001100000100000 .
b0 /
b100000 0
b1100000100000 1
bz 2
b1100000100000 3
b11 4
b1000001000110000010000000 6
07
0:
0;
0<
0?
1A
1B
b0 C
b1010 E
b10 F
b1000 G
b1000 H
b101000 I
b10000010001100000100000 J
b11 K
#350000
0!
b10 #
b1000 $
0(
#400000
1!
b1010 #
b10 $
b1100 %
b1000 &
1(
b11 *
b10 +
b10000 ,
b1000 -
b11000100010100000100010 .
b1 /
b100010 0
b10100000100010 1
bz 2
b10100000100010 3
b101 4
b1100010001010000010001000 6
07
0:
b1000 E
b1010 F
b10 G
b1100 H
b100000 I
b11000100010100000100010 J
b101 K
#450000
0!
b1010 #
b10 $
0(
#500000
1!
b1000 #
b10000 %
b0 &
1(
b101 *
b10100 ,
b0 -
b101000100010000000100100 .
b100 /
b100100 0
b10000000100100 1
bz 2
b10000000100100 3
b100 4
b10100010001000000010010000 6
17
0:
b0 C
b0 E
b1000 F
b10 G
b10000 H
b0 I
b101000100010000000100100 J
b100 K
#550000
0!
0(
#600000
1!
b0 #
b10100 %
b10 &
1(
b100 *
b11000 ,
b10 -
b100000100100000000100101 .
b11 /
b100101 0
b100000000100101 1
bz 2
b100000000100101 3
b1000 4
b10000010010000000010010100 6
07
0:
b0 C
b10 E
b0 F
b10 G
b10100 H
b1000 I
b100000100100000000100101 J
b1000 K
#650000
0!
b0 #
b10 $
0(
#700000
1!
b0 #
b10 $
b11000 %
b100 &
1(
b0 *
b1000 +
b11100 ,
b100 -
b10000100000001000000 .
b10 /
b0 0
b100000001000000 1
bz 2
b100000001000000 3
b1 5
b1000010000000100000000 6
07
1:
b100 E
b1 F
b10 G
b11000 H
b10000 I
b10000100000001000000 J
#750000
0!
b0 #
b100 $
b1000 &
0(
b1000 -
bz 2
07
b1000 E
b100 G
b100000 I
#800000
1!
b100 #
b1000 $
b11100 %
b11111111111111111111111111111100 &
b101 '
1(
b1000 *
b1 +
b1000000000000011000 ,
b11111111111111111111111111111100 -
b10101000000011111111111111110 .
b1 /
bx 0
b11111111111111111111111111111110 1
bz 2
b1111111111111110 3
b11111 4
b11111 5
b100000001111111111111111000 6
07
18
0:
0;
0<
0=
0?
1A
1B
b1 C
b11111111111111111111111111111100 E
b100 F
b1000 G
b11100 H
b11111111111111111111111111110000 I
b10101000000011111111111111110 J
b11111 K
#850000
0!
0(
#900000
1!
b0 #
b100 $
b11000 %
b1000 &
b0 '
1(
b0 *
b1000 +
b11100 ,
b1000 -
b10000100000001000000 .
b10 /
b0 0
b100000001000000 1
bz 2
b100000001000000 3
b1000 4
b1 5
b1000010000000100000000 6
07
08
1:
0;
0<
1=
0?
1A
1B
b0 C
b1000 E
b1 F
b100 G
b11000 H
b100000 I
b10000100000001000000 J
b1000 K
#950000
0!
b0 #
b1000 $
b10000 &
0(
b10000 -
bz 2
07
b10000 E
b1000 G
b1000000 I
#1000000
1!
b1000 #
b1000 $
b11100 %
b0 &
b101 '
1(
b1000 *
b1 +
b100000 ,
b0 -
b10101000000011111111111111110 .
b1 /
bx 0
b11111111111111111111111111111110 1
bz 2
b1111111111111110 3
b11111 4
b11111 5
b100000001111111111111111000 6
17
0:
0;
0<
0=
0?
1A
1B
b0 C
b0 E
b1000 F
b1000 G
b11100 H
b0 I
b10101000000011111111111111110 J
b11111 K
#1050000
0!
0(
#1100000
1!
b10 #
b0 $
b100000 %
b1 &
b1010 '
1(
b10 *
b110 +
b100100 ,
b1 -
b101000010001100000000000000100 .
b110 /
bx 0
b100 1
bz 2
b100 3
b0 4
b0 5
b1000110000000000000010000 6
07
0:
1;
0<
1=
0?
1A
0B
b0 C
b1 E
b10 F
b100 G
b100000 H
b100 I
b101000010001100000000000000100 J
b110 K
#1150000
0!
b10 #
b1 $
0(
b100 G
#1200000
1!
b1 #
b0 $
b100100 %
b0 &
1(
b110 *
b111 +
b101000 ,
b0 -
b101000110001110000000000000000 .
bx 0
b0 1
bz 2
b0 3
b11000111000000000000000000 6
17
b0 C
b0 E
b1 F
b0 G
b100100 H
b0 I
b101000110001110000000000000000 J
b111 K
#1250000
0!
0(
#1300000
1!
b0 #
b101000 %
b1000 &
b1001 '
1(
b111 *
b101100 ,
b1000 -
b100100111001110000000000001000 .
b0 /
bx 0
b1000 1
bz 2
b1000 3
b11100111000000000000100000 6
07
0:
1;
0<
0?
1A
0B
b0 C
b1000 E
b0 F
b1000 G
b101000 H
b100000 I
b100100111001110000000000001000 J
#1350000
0!
b1000 #
b1000 $
b10000 &
0(
b10000 -
bz 2
07
b10000 E
b1000 F
b1000 G
b1000000 I
#1400000
1!
b1000 $
b101100 %
b0 &
b100 '
1(
b1 +
b1000000000000101000 ,
b0 -
b10000111000011111111111111110 .
b1 /
bx 0
b11111111111111111111111111111110 1
bz 2
b1111111111111110 3
b11111 4
b11111 5
b11100001111111111111111000 6
17
0:
0;
0<
0=
0?
1A
1B
b1 C
b0 E
b1000 F
b1000 G
b101100 H
b0 I
b10000111000011111111111111110 J
b11111 K
#1450000
0!
0(
#1500000
1!
b1000 $
b101000 %
b10000 &
b1001 '
1(
b111 +
b101100 ,
b10000 -
b100100111001110000000000001000 .
b0 /
bx 0
b1000 1
bz 2
b1000 3
b0 4
b0 5
b11100111000000000000100000 6
07
0:
1;
0<
1=
0?
1A
0B
b0 C
b10000 E
b1000 F
b1000 G
b101000 H
b1000000 I
b100100111001110000000000001000 J
b111 K
#1550000
0!
b10000 #
b10000 $
b11000 &
0(
b11000 -
bz 2
07
b11000 E
b10000 F
b1000 G
b1100000 I
#1600000
1!
b1000 $
b101100 %
b1000 &
b100 '
1(
b1 +
b110000 ,
b1000 -
b10000111000011111111111111110 .
b1 /
bx 0
b11111111111111111111111111111110 1
bz 2
b1111111111111110 3
b11111 4
b11111 5
b11100001111111111111111000 6
07
0:
0;
0<
0=
0?
1A
1B
b0 C
b1000 E
b10000 F
b1000 G
b101100 H
b100000 I
b10000111000011111111111111110 J
b11111 K
#1650000
0!
0(
#1700000
1!
b1000 #
b10 $
b110000 %
b1100 &
b101011 '
1(
b1 *
b10 +
b110100 ,
b1100 -
b10101100001000100000000000000100 .
b0 /
bx 0
b100 1
bz 2
b100 3
b0 4
b0 5
b100010000000000000010000 6
07
0:
1;
0<
0?
1@
1A
1B
b0 C
b1100 E
b1000 F
b100 G
b110000 H
b110000 I
b10101100001000100000000000000100 J
b0 K
#1750000
0!
0(
bz 2
#1800000
1!
b0 $
b110100 %
b100011 '
1(
b1001 +
b111000 ,
b10 -
b10001100001010010000000000000100 .
b0 /
bx 0
b10 2
b101001000000000000010000 6
0:
1;
1<
1=
1?
0@
1A
0B
b0 C
b100 G
b110100 H
b10001100001010010000000000000100 J
b1001 K
#1850000
0!
b1000 #
b10 $
0(
b100 G
#1900000
1!
b0 #
b0 $
b111000 %
b11111111111111111111111111111110 &
b1001 '
1(
b0 *
b1010 +
b111100 ,
b11111111111111111111111111111110 -
b100100000010101111111111111110 .
b0 /
bx 0
b11111111111111111111111111111110 1
bz 2
b1111111111111110 3
b11111 4
b11111 5
b1010111111111111111000 6
07
18
0:
1;
0<
0?
1A
0B
b0 C
b11111111111111111111111111111110 E
b0 F
b11111111111111111111111111111110 G
b111000 H
b11111111111111111111111111111000 I
b100100000010101111111111111110 J
b1010 K
#1950000
0!
b0 #
b11111111111111111111111111111110 $
0(
b11111111111111111111111111111110 G
#2000000
1!
b11111111111111111111111111111110 #
b111100 %
b11111111111111111111111111111111 &
1(
b1010 *
b1000000 ,
b11111111111111111111111111111111 -
b100101010010100000000000000001 .
bx 0
b1 1
bz 2
b1 3
b0 4
b0 5
b101001010000000000000000100 6
07
b11111111111111111111111111111111 E
b11111111111111111111111111111110 F
b1 G
b111100 H
b11111111111111111111111111111100 I
b100101010010100000000000000001 J
#2050000
0!
b11111111111111111111111111111111 #
b11111111111111111111111111111111 $
b0 &
0(
b0 -
bz 2
17
08
b0 C
b0 E
b11111111111111111111111111111111 F
b1 G
b0 I
#2100000
1!
b0 $
b1000000 %
b11111111111111111111111111111111 &
b110 '
1(
b0 +
b1000000000000111100 ,
b11111111111111111111111111111111 -
b11001010000001111111111111110 .
b1 /
bx 0
b11111111111111111111111111111110 1
bz 2
b1111111111111110 3
b11111 4
b11111 5
b101000000111111111111111000 6
07
18
0:
0;
0<
0=
0?
1A
1B
b1 C
b11111111111111111111111111111111 E
b11111111111111111111111111111111 F
b0 G
b1000000 H
b11111111111111111111111111111100 I
b11001010000001111111111111110 J
b11111 K
#2150000
0!
0(
